Metadata-Version: 1.1
Name: KafkaLogs
Version: 0.0.10
Summary: Kakfa logging made simple with python, make your log messages as kafka events out-of-the-box!
Home-page: http://example.com
Author: mohammed yousuf uddin
Author-email: reach2yousuf@gmail.com
License: MIT
Keywords: kafka python logging
Platform: UNKNOWN
Classifier: Development Status :: 5 - Production/Stable
Classifier: Topic :: Utilities
Classifier: License :: OSI Approved :: MIT License
